minlizhash/LSH.py
minlizhash/__init__.py
minlizhash/hash.py
minlizhash/jit.py
minlizhash/min_hash.py
minlizhash/tokens.py
minlizhash/types.py
minlizhash/utils.py
minlizhash-0.2.1.dist-info/LICENSE
minlizhash-0.2.1.dist-info/METADATA
minlizhash-0.2.1.dist-info/WHEEL
minlizhash-0.2.1.dist-info/RECORD
