Metadata-Version: 2.1
Name: minlizhash
Version: 0.2.1
Summary: A simple MinHash LSH Implimentation from scratch
License: MIT
Author: Liz Goodwin
Author-email: work@lizgood.win
Requires-Python: >=3.11,<3.12
Classifier: License :: OSI Approved :: MIT License
Classifier: Programming Language :: Python :: 3
Classifier: Programming Language :: Python :: 3.11
Requires-Dist: jsonlines (>=4.0.0,<5.0.0)
Requires-Dist: numba (>=0.58.1,<0.59.0)
Requires-Dist: numpy (>=1.26.1,<2.0.0)
Requires-Dist: tdqm (>=0.0.1,<0.0.2)
Requires-Dist: tiktoken (>=0.5.1,<0.6.0)
Requires-Dist: types-tqdm (>=4.66.0.3,<5.0.0.0)
Requires-Dist: xxhash (>=3.4.1,<4.0.0)
